bilu/__init__.py
bilu/database/__init__.py
bilu/database/base.py
bilu/database/mongo.py
bilu/database/tests/__init__.py
bilu/database/tests/test_mongo.py
bilu/model/__init__.py
bilu/model/base.py
bilu/model/database.py
bilu/model/model.py
bilu/model/tests/__init__.py
bilu/model/tests/conftest.py
bilu/model/tests/test_model.py
bilu/tests/__init__.py
Bilu-0.0.3.dist-info/LICENSE
Bilu-0.0.3.dist-info/METADATA
Bilu-0.0.3.dist-info/WHEEL
Bilu-0.0.3.dist-info/top_level.txt
Bilu-0.0.3.dist-info/RECORD
