Metadata-Version: 2.1
Name: Bilu
Version: 0.0.3
Summary: Asynchronous ODM (Object Document Mapper) for MongoDB
Home-page: https://github.com/maikomjames/bilu
Author: maikomjames
Author-email: eu@maikom.com.br
License: UNKNOWN
Project-URL: Bug Tracker, https://github.com/maikomjames/bilu/issues
Platform: UNKNOWN
Classifier: Programming Language :: Python :: 3
Classifier: License :: OSI Approved :: MIT License
Classifier: Operating System :: OS Independent
Requires-Python: >=3.6
License-File: LICENSE
